wsgi_lineprof/formatter.py
wsgi_lineprof/version.py
wsgi_lineprof/extensions.pyi
wsgi_lineprof/__init__.py
wsgi_lineprof/types.py
wsgi_lineprof/writers.py
wsgi_lineprof/extensions.cpython-38-darwin.so
wsgi_lineprof/stats.py
wsgi_lineprof/app.py
wsgi_lineprof/py.typed
wsgi_lineprof/profiler.py
wsgi_lineprof/filters.py
wsgi_lineprof/middleware.py
wsgi_lineprof/templates/index.html
wsgi_lineprof/templates/base.html
wsgi_lineprof/templates/detail.html
extensions/timer.c
extensions/header.pxd
extensions/extensions.c
extensions/timer.h
extensions/extensions.pyx
wsgi_lineprof-0.19.1.dist-info/RECORD
wsgi_lineprof-0.19.1.dist-info/LICENSE
wsgi_lineprof-0.19.1.dist-info/WHEEL
wsgi_lineprof-0.19.1.dist-info/top_level.txt
wsgi_lineprof-0.19.1.dist-info/METADATA
