Metadata-Version: 2.1
Name: wsgi_lineprof
Version: 0.19.1
Summary: WSGI middleware for line-by-line profiling
Author-email: Yusuke Miyazaki <miyazaki.dev@gmail.com>
License: MIT License
Project-URL: Documentation, https://wsgi-lineprof.readthedocs.io
Project-URL: Source, https://github.com/ymyzk/wsgi_lineprof
Classifier: Development Status :: 3 - Alpha
Classifier: Intended Audience :: Developers
Classifier: License :: OSI Approved :: MIT License
Classifier: Operating System :: MacOS :: MacOS X
Classifier: Operating System :: Microsoft :: Windows
Classifier: Operating System :: POSIX
Classifier: Operating System :: Unix
Classifier: Programming Language :: C
Classifier: Programming Language :: Cython
Classifier: Programming Language :: Python :: 3
Classifier: Programming Language :: Python :: 3 :: Only
Classifier: Programming Language :: Python :: 3.8
Classifier: Programming Language :: Python :: 3.9
Classifier: Programming Language :: Python :: 3.10
Classifier: Programming Language :: Python :: 3.11
Classifier: Programming Language :: Python :: 3.12
Classifier: Programming Language :: Python :: Implementation :: CPython
Classifier: Topic :: Internet :: WWW/HTTP :: WSGI :: Middleware
Classifier: Topic :: Software Development
Classifier: Topic :: System :: Benchmark
Requires-Python: >=3.8
License-File: LICENSE
Requires-Dist: colorama >=0.4.1
Requires-Dist: Jinja2
Requires-Dist: pytz
Requires-Dist: typing-extensions
Provides-Extra: benchmark
Requires-Dist: asv <0.5,>=0.4 ; extra == 'benchmark'
Requires-Dist: virtualenv ; extra == 'benchmark'
Provides-Extra: benchmark-deps
Requires-Dist: Jinja2 ==2.10 ; extra == 'benchmark-deps'
Requires-Dist: WebTest ==2.0.32 ; extra == 'benchmark-deps'
Provides-Extra: docs
Requires-Dist: Sphinx <7,>=6 ; extra == 'docs'
Requires-Dist: sphinx-rtd-theme <2,>=1 ; extra == 'docs'
Provides-Extra: test
Requires-Dist: mypy <2,>=1 ; extra == 'test'
Requires-Dist: pytest <8,>=7 ; extra == 'test'
Requires-Dist: pytest-cov <5,>=4 ; extra == 'test'
Requires-Dist: pytest-mock >=1.11 ; extra == 'test'
Requires-Dist: pytest-randomly ; extra == 'test'
Requires-Dist: types-colorama ; extra == 'test'
Requires-Dist: types-pytz ; extra == 'test'
